LICENSE.txt
README.md
pyproject.toml
setup.cfg
setup.py
kate_vscode_snippetconverter.egg-info/PKG-INFO
kate_vscode_snippetconverter.egg-info/SOURCES.txt
kate_vscode_snippetconverter.egg-info/dependency_links.txt
kate_vscode_snippetconverter.egg-info/entry_points.txt
kate_vscode_snippetconverter.egg-info/top_level.txt
snippetconverter/__init__.py
snippetconverter/languages.py
snippetconverter/snippetconverter.py