Metadata-Version: 2.1
Name: kate-vscode-snippetconverter
Version: 0.3.3
Summary: A tool to convert snippet from Kate/KDevelop to VSCode
Home-page: https://github.com/renn0xtek9/snippetconverter
Author: Maxime Haselbauer
Author-email: maxime.haselbauer@googlemail.com
License: UNKNOWN
Platform: UNKNOWN
License-File: LICENSE.txt
